fixkit/__init__.py
fixkit/candidate.py
fixkit/cli.py
fixkit/constants.py
fixkit/logger.py
fixkit/stmt.py
fixkit/analysis/__init__.py
fixkit/analysis/dataflow.py
fixkit/analysis/scope.py
fixkit/fitness/__init__.py
fixkit/fitness/engine.py
fixkit/fitness/metric.py
fixkit/genetic/__init__.py
fixkit/genetic/crossover.py
fixkit/genetic/minimize.py
fixkit/genetic/operators.py
fixkit/genetic/selection.py
fixkit/genetic/templates.py
fixkit/genetic/transform.py
fixkit/genetic/types.py
fixkit/localization/__init__.py
fixkit/localization/coverage.py
fixkit/localization/localization.py
fixkit/localization/location.py
fixkit/localization/normalization.py
fixkit/localization/sflkit.py
fixkit/localization/t4p.py
fixkit/repair/__init__.py
fixkit/repair/patch.py
fixkit/repair/pyae.py
fixkit/repair/pycardumen.py
fixkit/repair/pygenprog.py
fixkit/repair/pykali.py
fixkit/repair/pymutrepair.py
fixkit/repair/repair.py
fixkit/search/__init__.py
fixkit/search/search.py
fixkit/validation/__init__.py
fixkit/validation/validation.py
fixkit-0.0.1.dist-info/LICENSE
fixkit-0.0.1.dist-info/METADATA
fixkit-0.0.1.dist-info/WHEEL
fixkit-0.0.1.dist-info/entry_points.txt
fixkit-0.0.1.dist-info/top_level.txt
fixkit-0.0.1.dist-info/RECORD
