Metadata-Version: 2.1
Name: fixkit
Version: 0.0.1
Summary: PyRep is a collection of automatic program repair approaches in and for Python.
Author-email: Marius Smytzek <marius.smytzek@cispa.de>, Kai Werk <werkkai@hu-berlin.de>, Martin Eberlein <ebermart@informatik.hu-berlin.de>
Project-URL: Homepage, https://github.com/smythi93/fixkit
Project-URL: Bug Tracker, https://github.com/smythi93/fixkit/issues
Classifier: Intended Audience :: Science/Research
Classifier: License :: OSI Approved :: MIT License
Classifier: Programming Language :: Python :: 3.10
Classifier: Operating System :: OS Independent
Classifier: Topic :: Scientific/Engineering
Classifier: Topic :: Software Development :: Testing
Requires-Python: >=3.11
License-File: LICENSE
Requires-Dist: sflkit >=0.2.16
Requires-Dist: sflkitlib >=0.0.3
Requires-Dist: pytest >=8.0.2
Requires-Dist: pytest-cov >=4.1.0
Requires-Dist: pytest-json-report >=1.5.0
Requires-Dist: coverage >=7.4.3
Requires-Dist: numpy >=1.26.4
Requires-Dist: multiset >=3.1.0
Requires-Dist: tests4py >=0.0.7
Provides-Extra: test
Requires-Dist: pytest-html >=3.2.0 ; extra == 'test'
Requires-Dist: pytest-rerunfailures >=11.1.2 ; extra == 'test'
